langgate/sdk/__init__.py
langgate/sdk/client.py
langgate/sdk/protocol.py
langgate/sdk/py.typed
langgate_sdk-0.3.3.dist-info/METADATA
langgate_sdk-0.3.3.dist-info/WHEEL
langgate_sdk-0.3.3.dist-info/RECORD
