Metadata-Version: 2.4
Name: langgate-sdk
Version: 0.3.3
Summary: Convenience SDK for LangGate AI Gateway
Author: Tanantor Ltd.
Maintainer-email: Saran Connoly <saran@tanantor.com>
License: MIT
Requires-Python: >=3.13
Requires-Dist: langgate-core==0.3.3
Requires-Dist: langgate-registry==0.3.3
Requires-Dist: langgate-transform==0.3.3
